{
  "quickadd:choice:2ad994fe-7bc6-4208-b2e9-8ea6dc2190d6": [
    {
      "modifiers": [
        "Alt",
        "Mod"
      ],
      "key": "N"
    }
  ],
  "quickadd:choice:5bc0095a-a7e5-4042-9e8d-4c3808de88ef": [
    {
      "modifiers": [
        "Alt",
        "Mod"
      ],
      "key": "A"
    }
  ],
  "quickadd:choice:7c6b328e-63d7-4c39-a651-89dca742db82": [
    {
      "modifiers": [
        "Alt",
        "Mod"
      ],
      "key": "D"
    }
  ],
  "obsidian-hotkeys-for-specific-files:01 Algemeen/Planning/Taken/Inbox.md-new-tab": [
    {
      "modifiers": [
        "Alt",
        "Mod"
      ],
      "key": "I"
    }
  ],
  "obsidian-icons-plugin:open-icons-plugin-modal": [],
  "obsidian-tasks-plugin:edit-task": [
    {
      "modifiers": [
        "Alt"
      ],
      "key": "T"
    }
  ],
  "quick-explorer:go-next": [
    {
      "modifiers": [
        "Alt",
        "Mod"
      ],
      "key": "."
    }
  ],
  "quick-explorer:go-prev": [
    {
      "modifiers": [
        "Alt",
        "Mod"
      ],
      "key": ","
    }
  ],
  "insert-current-date": [
    {
      "modifiers": [
        "Alt",
        "Meta"
      ],
      "key": "T"
    }
  ],
  "insert-current-time": [
    {
      "modifiers": [
        "Alt",
        "Mod"
      ],
      "key": "T"
    }
  ]
}